COPYING
MANIFEST.in
README.txt
poste_replique.py
setup.py
poste_replique.egg-info/PKG-INFO
poste_replique.egg-info/SOURCES.txt
poste_replique.egg-info/dependency_links.txt
poste_replique.egg-info/top_level.txt