Metadata-Version: 1.0
Name: poste-replique
Version: 0.1.5
Summary:  CLI and Python API for client-side communication with a persistent REPL server.
Home-page: http://github.com/intuited/poste_replique
Author: Ted Tibbetts
Author-email: intuited@gmail.com
License: UNKNOWN
Keywords: node,client,repl
Platform: UNKNOWN
Classifier: Development Status :: 4 - Beta
Classifier: Intended Audience :: Developers
Classifier: License :: OSI Approved :: BSD License
Classifier: Operating System :: OS Independent
Classifier: Programming Language :: Python
Classifier: Programming Language :: Python :: 2
Classifier: Topic :: Utilities
Classifier: Topic :: Software Development :: User Interfaces
